leapseconddata/__init__.py
leapseconddata/__main__.py
leapseconddata/__version__.py
leapseconddata/py.typed
leapseconddata-4.1.1.dist-info/METADATA
leapseconddata-4.1.1.dist-info/WHEEL
leapseconddata-4.1.1.dist-info/entry_points.txt
leapseconddata-4.1.1.dist-info/top_level.txt
leapseconddata-4.1.1.dist-info/RECORD
