Metadata-Version: 2.4
Name: leapseconddata
Version: 4.1.1
Summary: Use the list of known and scheduled leap seconds
Author-email: Jeff Epler <jepler@gmail.com>
Project-URL: Source, https://github.com/jepler/leapseconddata
Project-URL: Documentation, https://leapseconddata.readthedocs.io/en/latest/
Classifier: Programming Language :: Python :: 3
Classifier: Programming Language :: Python :: 3.9
Classifier: Programming Language :: Python :: 3.10
Classifier: Programming Language :: Python :: 3.11
Classifier: Programming Language :: Python :: Implementation :: PyPy
Classifier: Programming Language :: Python :: Implementation :: CPython
Classifier: License :: OSI Approved :: GNU General Public License v3 (GPLv3)
Classifier: Operating System :: OS Independent
Requires-Python: >=3.9
Requires-Dist: click
